README.txt
plonetheme.andreas01-configure.zcml
setup.cfg
setup.py
docs/HISTORY.txt
docs/INSTALL.txt
docs/LICENSE.GPL
docs/LICENSE.txt
plonetheme/__init__.py
plonetheme.andreas01.egg-info/PKG-INFO
plonetheme.andreas01.egg-info/SOURCES.txt
plonetheme.andreas01.egg-info/dependency_links.txt
plonetheme.andreas01.egg-info/entry_points.txt
plonetheme.andreas01.egg-info/namespace_packages.txt
plonetheme.andreas01.egg-info/not-zip-safe
plonetheme.andreas01.egg-info/requires.txt
plonetheme.andreas01.egg-info/top_level.txt
plonetheme/andreas01/__init__.py
plonetheme/andreas01/configure.zcml
plonetheme/andreas01/profiles.zcml
plonetheme/andreas01/setuphandlers.py
plonetheme/andreas01/skins.zcml
plonetheme/andreas01/tests.py
plonetheme/andreas01/version.txt
plonetheme/andreas01/browser/__init__.py
plonetheme/andreas01/browser/configure.zcml
plonetheme/andreas01/browser/interfaces.py
plonetheme/andreas01/browser/viewlet.pt
plonetheme/andreas01/browser/viewlets.py
plonetheme/andreas01/browser/images/bg.gif
plonetheme/andreas01/browser/images/front.jpg
plonetheme/andreas01/browser/stylesheets/main.css
plonetheme/andreas01/browser/viewlets/page_title.pt
plonetheme/andreas01/profiles/default/cssregistry.xml
plonetheme/andreas01/profiles/default/import_steps.xml
plonetheme/andreas01/profiles/default/jsregistry.xml
plonetheme/andreas01/profiles/default/plonetheme.andreas01_various.txt
plonetheme/andreas01/profiles/default/skins.xml
plonetheme/andreas01/profiles/default/viewlets.xml
plonetheme/andreas01/skins/plonetheme_andreas01_styles/base.css.dtml
plonetheme/andreas01/skins/plonetheme_andreas01_styles/base_properties.props
plonetheme/andreas01/skins/plonetheme_andreas01_styles/portlets.css.dtml
plonetheme/andreas01/skins/plonetheme_andreas01_styles/public.css.dtml
